secure_aiohttp/__init__.py
secure_aiohttp/secure_setup.py
secure_aiohttp/settings.py
secure_aiohttp/utils.py
secure_aiohttp-0.0.24.dist-info/LICENSE
secure_aiohttp-0.0.24.dist-info/METADATA
secure_aiohttp-0.0.24.dist-info/WHEEL
secure_aiohttp-0.0.24.dist-info/top_level.txt
secure_aiohttp-0.0.24.dist-info/RECORD
