Metadata-Version: 2.1
Name: secure-aiohttp
Version: 0.0.24
Summary: aiohttp additional security layer
Home-page: https://github.com/pinlast/secure-aiohttp
Author: Danil Pekarchuk
Author-email: danilopekarchuk321@gmail.com
License: Apache 2
Platform: UNKNOWN
Classifier: License :: OSI Approved :: Apache Software License
Classifier: Intended Audience :: Developers
Classifier: Programming Language :: Python
Classifier: Programming Language :: Python :: 3.5
Classifier: Programming Language :: Python :: 3.6
Classifier: Programming Language :: Python :: 3.7
Classifier: Topic :: Internet :: WWW/HTTP
Classifier: Framework :: AsyncIO
Requires-Python: >=3.5
